{
  "klass": "Specie",
  "id": 658,
  "dbSymbol": "greninja",
  "forms": [
    {
      "form": 0,
      "formTextId": {
        "name": 853,
        "description": 0
      },
      "height": 1.5,
      "weight": 40,
      "type1": "water",
      "type2": "dark",
      "baseHp": 72,
      "baseAtk": 95,
      "baseDfe": 67,
      "baseSpd": 122,
      "baseAts": 103,
      "baseDfs": 71,
      "evHp": 0,
      "evAtk": 0,
      "evDfe": 0,
      "evSpd": 3,
      "evAts": 0,
      "evDfs": 0,
      "evolutions": [
        {
          "form": 30,
          "conditions": [
            {
              "type": "gemme",
              "value": "greninjite"
            }
          ]
        }
      ],
      "experienceType": 3,
      "baseExperience": 239,
      "baseLoyalty": 50,
      "catchRate": 45,
      "femaleRate": 12.5,
      "breedGroups": [
        2,
        2
      ],
      "hatchSteps": 2560,
      "babyDbSymbol": "froakie",
      "babyForm": 0,
      "itemHeld": [
        {
          "dbSymbol": "none",
          "chance": 0
        },
        {
          "dbSymbol": "none",
          "chance": 0
        }
      ],
      "abilities": [
        "torrent",
        "protean",
        "battle_bond"
      ],
      "frontOffsetY": 0,
      "resources": {
        "icon": "0658",
        "iconShiny": "0658s",
        "front": "0658",
        "frontShiny": "0658s",
        "back": "0658",
        "backShiny": "0658s",
        "footprint": "0658",
        "character": "0658",
        "characterShiny": "0658s",
        "egg": "egg",
        "iconEgg": "egg",
        "cry": "0658.ogg",
        "hasFemale": false
      },
      "moveSet": [
        {
          "klass": "LevelLearnableMove",
          "move": "pound",
          "level": 1
        },
        {
          "klass": "LevelLearnableMove",
          "move": "growl",
          "level": 1
        },
        {
          "klass": "LevelLearnableMove",
          "move": "water_gun",
          "level": 1
        },
        {
          "klass": "LevelLearnableMove",
          "move": "quick_attack",
          "level": 1
        },
        {
          "klass": "LevelLearnableMove",
          "move": "haze",
          "level": 1
        },
        {
          "klass": "LevelLearnableMove",
          "move": "role_play",
          "level": 1
        },
        {
          "klass": "LevelLearnableMove",
          "move": "night_slash",
          "level": 1
        },
        {
          "klass": "LevelLearnableMove",
          "move": "lick",
          "level": 10
        },
        {
          "klass": "LevelLearnableMove",
          "move": "water_pulse",
          "level": 14
        },
        {
          "klass": "LevelLearnableMove",
          "move": "smokescreen",
          "level": 19
        },
        {
          "klass": "LevelLearnableMove",
          "move": "shadow_sneak",
          "level": 23
        },
        {
          "klass": "LevelLearnableMove",
          "move": "spikes",
          "level": 28
        },
        {
          "klass": "LevelLearnableMove",
          "move": "aerial_ace",
          "level": 33
        },
        {
          "klass": "LevelLearnableMove",
          "move": "substitute",
          "level": 42
        },
        {
          "klass": "LevelLearnableMove",
          "move": "extrasensory",
          "level": 49
        },
        {
          "klass": "LevelLearnableMove",
          "move": "double_team",
          "level": 56
        },
        {
          "klass": "LevelLearnableMove",
          "move": "hydro_pump",
          "level": 68
        },
        {
          "klass": "TechLearnableMove",
          "move": "ice_punch"
        },
        {
          "klass": "TechLearnableMove",
          "move": "swords_dance"
        },
        {
          "klass": "TechLearnableMove",
          "move": "take_down"
        },
        {
          "klass": "TechLearnableMove",
          "move": "hydro_pump"
        },
        {
          "klass": "TechLearnableMove",
          "move": "surf"
        },
        {
          "klass": "TechLearnableMove",
          "move": "ice_beam"
        },
        {
          "klass": "TechLearnableMove",
          "move": "blizzard"
        },
        {
          "klass": "TechLearnableMove",
          "move": "hyper_beam"
        },
        {
          "klass": "TechLearnableMove",
          "move": "low_kick"
        },
        {
          "klass": "BreedLearnableMove",
          "move": "counter"
        },
        {
          "klass": "TechLearnableMove",
          "move": "dig"
        },
        {
          "klass": "TechLearnableMove",
          "move": "haze"
        },
        {
          "klass": "TechLearnableMove",
          "move": "waterfall"
        },
        {
          "klass": "TechLearnableMove",
          "move": "swift"
        },
        {
          "klass": "TechLearnableMove",
          "move": "rest"
        },
        {
          "klass": "TechLearnableMove",
          "move": "rock_slide"
        },
        {
          "klass": "TechLearnableMove",
          "move": "substitute"
        },
        {
          "klass": "TechLearnableMove",
          "move": "thief"
        },
        {
          "klass": "TechLearnableMove",
          "move": "protect"
        },
        {
          "klass": "TechLearnableMove",
          "move": "mud_slap"
        },
        {
          "klass": "BreedLearnableMove",
          "move": "spikes"
        },
        {
          "klass": "TechLearnableMove",
          "move": "spikes"
        },
        {
          "klass": "TechLearnableMove",
          "move": "icy_wind"
        },
        {
          "klass": "TechLearnableMove",
          "move": "endure"
        },
        {
          "klass": "TechLearnableMove",
          "move": "false_swipe"
        },
        {
          "klass": "TechLearnableMove",
          "move": "sleep_talk"
        },
        {
          "klass": "TechLearnableMove",
          "move": "rain_dance"
        },
        {
          "klass": "TechLearnableMove",
          "move": "facade"
        },
        {
          "klass": "TechLearnableMove",
          "move": "taunt"
        },
        {
          "klass": "TechLearnableMove",
          "move": "helping_hand"
        },
        {
          "klass": "TechLearnableMove",
          "move": "brick_break"
        },
        {
          "klass": "TechLearnableMove",
          "move": "hydro_cannon"
        },
        {
          "klass": "TechLearnableMove",
          "move": "weather_ball"
        },
        {
          "klass": "TechLearnableMove",
          "move": "rock_tomb"
        },
        {
          "klass": "TechLearnableMove",
          "move": "aerial_ace"
        },
        {
          "klass": "TechLearnableMove",
          "move": "mud_shot"
        },
        {
          "klass": "TechLearnableMove",
          "move": "water_pulse"
        },
        {
          "klass": "TechLearnableMove",
          "move": "u_turn"
        },
        {
          "klass": "TechLearnableMove",
          "move": "fling"
        },
        {
          "klass": "BreedLearnableMove",
          "move": "toxic_spikes"
        },
        {
          "klass": "TechLearnableMove",
          "move": "toxic_spikes"
        },
        {
          "klass": "TechLearnableMove",
          "move": "dark_pulse"
        },
        {
          "klass": "BreedLearnableMove",
          "move": "switcheroo"
        },
        {
          "klass": "TechLearnableMove",
          "move": "giga_impact"
        },
        {
          "klass": "TechLearnableMove",
          "move": "gunk_shot"
        },
        {
          "klass": "TechLearnableMove",
          "move": "grass_knot"
        },
        {
          "klass": "TechLearnableMove",
          "move": "smack_down"
        },
        {
          "klass": "TechLearnableMove",
          "move": "sludge_wave"
        },
        {
          "klass": "TechLearnableMove",
          "move": "low_sweep"
        },
        {
          "klass": "TechLearnableMove",
          "move": "acrobatics"
        },
        {
          "klass": "BreedLearnableMove",
          "move": "retaliate"
        },
        {
          "klass": "TechLearnableMove",
          "move": "water_pledge"
        },
        {
          "klass": "EvolutionLearnableMove",
          "move": "water_shuriken"
        },
        {
          "klass": "TechLearnableMove",
          "move": "liquidation"
        },
        {
          "klass": "TechLearnableMove",
          "move": "tera_blast"
        },
        {
          "klass": "TechLearnableMove",
          "move": "snowscape"
        },
        {
          "klass": "TechLearnableMove",
          "move": "trailblaze"
        },
        {
          "klass": "TechLearnableMove",
          "move": "chilling_water"
        },
        {
          "klass": "TechLearnableMove",
          "move": "upper_hand"
        },
        {
          "klass": "TechLearnableMove",
          "move": "rock_smash"
        },
        {
          "klass": "TechLearnableMove",
          "move": "cut"
        },
        {
          "klass": "TechLearnableMove",
          "move": "strength"
        },
        {
          "klass": "TechLearnableMove",
          "move": "dive"
        }
      ]
    },
    {
      "form": 1,
      "formTextId": {
        "name": 854,
        "description": 197
      },
      "height": 1.5,
      "weight": 40,
      "type1": "water",
      "type2": "dark",
      "baseHp": 72,
      "baseAtk": 145,
      "baseDfe": 67,
      "baseSpd": 132,
      "baseAts": 153,
      "baseDfs": 71,
      "evHp": 0,
      "evAtk": 0,
      "evDfe": 0,
      "evSpd": 3,
      "evAts": 0,
      "evDfs": 0,
      "evolutions": [],
      "experienceType": 3,
      "baseExperience": 239,
      "baseLoyalty": 50,
      "catchRate": 45,
      "femaleRate": 12.5,
      "breedGroups": [
        2,
        2
      ],
      "hatchSteps": 2677,
      "babyDbSymbol": "froakie",
      "babyForm": 1,
      "itemHeld": [
        {
          "dbSymbol": "none",
          "chance": 0
        },
        {
          "dbSymbol": "none",
          "chance": 0
        }
      ],
      "abilities": [
        "torrent",
        "torrent",
        "battle_bond"
      ],
      "frontOffsetY": 0,
      "resources": {
        "icon": "0658_01",
        "iconShiny": "0658s_01",
        "front": "0658_01",
        "frontShiny": "0658s_01",
        "back": "0658_01",
        "backShiny": "0658s_01",
        "footprint": "0658",
        "character": "0658_01",
        "characterShiny": "0658s_01",
        "egg": "egg",
        "iconEgg": "egg",
        "cry": "0658.ogg",
        "hasFemale": false
      },
      "moveSet": [
        {
          "klass": "LevelLearnableMove",
          "move": "pound",
          "level": 1
        },
        {
          "klass": "LevelLearnableMove",
          "move": "growl",
          "level": 1
        },
        {
          "klass": "LevelLearnableMove",
          "move": "water_gun",
          "level": 1
        },
        {
          "klass": "LevelLearnableMove",
          "move": "quick_attack",
          "level": 1
        },
        {
          "klass": "LevelLearnableMove",
          "move": "haze",
          "level": 1
        },
        {
          "klass": "LevelLearnableMove",
          "move": "role_play",
          "level": 1
        },
        {
          "klass": "LevelLearnableMove",
          "move": "night_slash",
          "level": 1
        },
        {
          "klass": "LevelLearnableMove",
          "move": "lick",
          "level": 10
        },
        {
          "klass": "LevelLearnableMove",
          "move": "water_pulse",
          "level": 14
        },
        {
          "klass": "LevelLearnableMove",
          "move": "smokescreen",
          "level": 19
        },
        {
          "klass": "LevelLearnableMove",
          "move": "shadow_sneak",
          "level": 23
        },
        {
          "klass": "LevelLearnableMove",
          "move": "spikes",
          "level": 28
        },
        {
          "klass": "LevelLearnableMove",
          "move": "aerial_ace",
          "level": 33
        },
        {
          "klass": "LevelLearnableMove",
          "move": "substitute",
          "level": 42
        },
        {
          "klass": "LevelLearnableMove",
          "move": "extrasensory",
          "level": 49
        },
        {
          "klass": "LevelLearnableMove",
          "move": "double_team",
          "level": 56
        },
        {
          "klass": "LevelLearnableMove",
          "move": "hydro_pump",
          "level": 68
        },
        {
          "klass": "TechLearnableMove",
          "move": "ice_punch"
        },
        {
          "klass": "TechLearnableMove",
          "move": "swords_dance"
        },
        {
          "klass": "TechLearnableMove",
          "move": "take_down"
        },
        {
          "klass": "TechLearnableMove",
          "move": "hydro_pump"
        },
        {
          "klass": "TechLearnableMove",
          "move": "surf"
        },
        {
          "klass": "TechLearnableMove",
          "move": "ice_beam"
        },
        {
          "klass": "TechLearnableMove",
          "move": "blizzard"
        },
        {
          "klass": "TechLearnableMove",
          "move": "hyper_beam"
        },
        {
          "klass": "TechLearnableMove",
          "move": "low_kick"
        },
        {
          "klass": "BreedLearnableMove",
          "move": "counter"
        },
        {
          "klass": "TechLearnableMove",
          "move": "dig"
        },
        {
          "klass": "TechLearnableMove",
          "move": "haze"
        },
        {
          "klass": "TechLearnableMove",
          "move": "waterfall"
        },
        {
          "klass": "TechLearnableMove",
          "move": "swift"
        },
        {
          "klass": "TechLearnableMove",
          "move": "rest"
        },
        {
          "klass": "TechLearnableMove",
          "move": "rock_slide"
        },
        {
          "klass": "TechLearnableMove",
          "move": "substitute"
        },
        {
          "klass": "TechLearnableMove",
          "move": "thief"
        },
        {
          "klass": "TechLearnableMove",
          "move": "protect"
        },
        {
          "klass": "TechLearnableMove",
          "move": "mud_slap"
        },
        {
          "klass": "BreedLearnableMove",
          "move": "spikes"
        },
        {
          "klass": "TechLearnableMove",
          "move": "spikes"
        },
        {
          "klass": "TechLearnableMove",
          "move": "icy_wind"
        },
        {
          "klass": "TechLearnableMove",
          "move": "endure"
        },
        {
          "klass": "TechLearnableMove",
          "move": "false_swipe"
        },
        {
          "klass": "TechLearnableMove",
          "move": "sleep_talk"
        },
        {
          "klass": "TechLearnableMove",
          "move": "rain_dance"
        },
        {
          "klass": "TechLearnableMove",
          "move": "facade"
        },
        {
          "klass": "TechLearnableMove",
          "move": "taunt"
        },
        {
          "klass": "TechLearnableMove",
          "move": "helping_hand"
        },
        {
          "klass": "TechLearnableMove",
          "move": "brick_break"
        },
        {
          "klass": "TechLearnableMove",
          "move": "hydro_cannon"
        },
        {
          "klass": "TechLearnableMove",
          "move": "weather_ball"
        },
        {
          "klass": "TechLearnableMove",
          "move": "rock_tomb"
        },
        {
          "klass": "TechLearnableMove",
          "move": "aerial_ace"
        },
        {
          "klass": "TechLearnableMove",
          "move": "mud_shot"
        },
        {
          "klass": "TechLearnableMove",
          "move": "water_pulse"
        },
        {
          "klass": "TechLearnableMove",
          "move": "u_turn"
        },
        {
          "klass": "TechLearnableMove",
          "move": "fling"
        },
        {
          "klass": "BreedLearnableMove",
          "move": "toxic_spikes"
        },
        {
          "klass": "TechLearnableMove",
          "move": "toxic_spikes"
        },
        {
          "klass": "TechLearnableMove",
          "move": "dark_pulse"
        },
        {
          "klass": "BreedLearnableMove",
          "move": "switcheroo"
        },
        {
          "klass": "TechLearnableMove",
          "move": "giga_impact"
        },
        {
          "klass": "TechLearnableMove",
          "move": "gunk_shot"
        },
        {
          "klass": "TechLearnableMove",
          "move": "grass_knot"
        },
        {
          "klass": "TechLearnableMove",
          "move": "smack_down"
        },
        {
          "klass": "TechLearnableMove",
          "move": "sludge_wave"
        },
        {
          "klass": "TechLearnableMove",
          "move": "low_sweep"
        },
        {
          "klass": "TechLearnableMove",
          "move": "acrobatics"
        },
        {
          "klass": "BreedLearnableMove",
          "move": "retaliate"
        },
        {
          "klass": "TechLearnableMove",
          "move": "water_pledge"
        },
        {
          "klass": "EvolutionLearnableMove",
          "move": "water_shuriken"
        },
        {
          "klass": "TechLearnableMove",
          "move": "liquidation"
        },
        {
          "klass": "TechLearnableMove",
          "move": "tera_blast"
        },
        {
          "klass": "TechLearnableMove",
          "move": "snowscape"
        },
        {
          "klass": "TechLearnableMove",
          "move": "trailblaze"
        },
        {
          "klass": "TechLearnableMove",
          "move": "chilling_water"
        },
        {
          "klass": "TechLearnableMove",
          "move": "upper_hand"
        },
        {
          "klass": "TechLearnableMove",
          "move": "rock_smash"
        },
        {
          "klass": "TechLearnableMove",
          "move": "cut"
        },
        {
          "klass": "TechLearnableMove",
          "move": "strength"
        },
        {
          "klass": "TechLearnableMove",
          "move": "dive"
        }
      ]
    },
    {
      "form": 30,
      "formTextId": {
        "name": 1403,
        "description": 379
      },
      "height": 1.5,
      "weight": 40,
      "type1": "water",
      "type2": "dark",
      "baseHp": 72,
      "baseAtk": 125,
      "baseDfe": 77,
      "baseSpd": 142,
      "baseAts": 133,
      "baseDfs": 81,
      "evHp": 0,
      "evAtk": 0,
      "evDfe": 0,
      "evSpd": 3,
      "evAts": 0,
      "evDfs": 0,
      "evolutions": [],
      "experienceType": 3,
      "baseExperience": 239,
      "baseLoyalty": 50,
      "catchRate": 45,
      "femaleRate": 12.5,
      "breedGroups": [
        2,
        2
      ],
      "hatchSteps": 2560,
      "babyDbSymbol": "froakie",
      "babyForm": 0,
      "itemHeld": [
        {
          "dbSymbol": "none",
          "chance": 0
        },
        {
          "dbSymbol": "none",
          "chance": 0
        }
      ],
      "abilities": [
        "torrent",
        "torrent",
        "protean"
      ],
      "frontOffsetY": 0,
      "resources": {
        "icon": "0658_30",
        "iconShiny": "0658s_30",
        "front": "0658_30",
        "frontShiny": "0658s_30",
        "back": "0658_30",
        "backShiny": "0658s_30",
        "footprint": "0658",
        "character": "",
        "characterShiny": "",
        "egg": "egg",
        "iconEgg": "egg",
        "cry": "0658.ogg",
        "hasFemale": false
      },
      "moveSet": [
        {
          "klass": "LevelLearnableMove",
          "move": "pound",
          "level": 1
        },
        {
          "klass": "LevelLearnableMove",
          "move": "growl",
          "level": 1
        },
        {
          "klass": "LevelLearnableMove",
          "move": "water_gun",
          "level": 1
        },
        {
          "klass": "LevelLearnableMove",
          "move": "quick_attack",
          "level": 1
        },
        {
          "klass": "LevelLearnableMove",
          "move": "haze",
          "level": 1
        },
        {
          "klass": "LevelLearnableMove",
          "move": "role_play",
          "level": 1
        },
        {
          "klass": "LevelLearnableMove",
          "move": "night_slash",
          "level": 1
        },
        {
          "klass": "LevelLearnableMove",
          "move": "lick",
          "level": 10
        },
        {
          "klass": "LevelLearnableMove",
          "move": "water_pulse",
          "level": 14
        },
        {
          "klass": "LevelLearnableMove",
          "move": "smokescreen",
          "level": 19
        },
        {
          "klass": "LevelLearnableMove",
          "move": "shadow_sneak",
          "level": 23
        },
        {
          "klass": "LevelLearnableMove",
          "move": "spikes",
          "level": 28
        },
        {
          "klass": "LevelLearnableMove",
          "move": "aerial_ace",
          "level": 33
        },
        {
          "klass": "LevelLearnableMove",
          "move": "substitute",
          "level": 42
        },
        {
          "klass": "LevelLearnableMove",
          "move": "extrasensory",
          "level": 49
        },
        {
          "klass": "LevelLearnableMove",
          "move": "double_team",
          "level": 56
        },
        {
          "klass": "LevelLearnableMove",
          "move": "hydro_pump",
          "level": 68
        },
        {
          "klass": "TechLearnableMove",
          "move": "ice_punch"
        },
        {
          "klass": "TechLearnableMove",
          "move": "swords_dance"
        },
        {
          "klass": "TechLearnableMove",
          "move": "take_down"
        },
        {
          "klass": "TechLearnableMove",
          "move": "hydro_pump"
        },
        {
          "klass": "TechLearnableMove",
          "move": "surf"
        },
        {
          "klass": "TechLearnableMove",
          "move": "ice_beam"
        },
        {
          "klass": "TechLearnableMove",
          "move": "blizzard"
        },
        {
          "klass": "TechLearnableMove",
          "move": "hyper_beam"
        },
        {
          "klass": "TechLearnableMove",
          "move": "low_kick"
        },
        {
          "klass": "BreedLearnableMove",
          "move": "counter"
        },
        {
          "klass": "TechLearnableMove",
          "move": "dig"
        },
        {
          "klass": "TechLearnableMove",
          "move": "haze"
        },
        {
          "klass": "TechLearnableMove",
          "move": "waterfall"
        },
        {
          "klass": "TechLearnableMove",
          "move": "swift"
        },
        {
          "klass": "TechLearnableMove",
          "move": "rest"
        },
        {
          "klass": "TechLearnableMove",
          "move": "rock_slide"
        },
        {
          "klass": "TechLearnableMove",
          "move": "substitute"
        },
        {
          "klass": "TechLearnableMove",
          "move": "thief"
        },
        {
          "klass": "TechLearnableMove",
          "move": "protect"
        },
        {
          "klass": "TechLearnableMove",
          "move": "mud_slap"
        },
        {
          "klass": "BreedLearnableMove",
          "move": "spikes"
        },
        {
          "klass": "TechLearnableMove",
          "move": "spikes"
        },
        {
          "klass": "TechLearnableMove",
          "move": "icy_wind"
        },
        {
          "klass": "TechLearnableMove",
          "move": "endure"
        },
        {
          "klass": "TechLearnableMove",
          "move": "false_swipe"
        },
        {
          "klass": "TechLearnableMove",
          "move": "sleep_talk"
        },
        {
          "klass": "TechLearnableMove",
          "move": "rain_dance"
        },
        {
          "klass": "TechLearnableMove",
          "move": "facade"
        },
        {
          "klass": "TechLearnableMove",
          "move": "taunt"
        },
        {
          "klass": "TechLearnableMove",
          "move": "helping_hand"
        },
        {
          "klass": "TechLearnableMove",
          "move": "brick_break"
        },
        {
          "klass": "TechLearnableMove",
          "move": "hydro_cannon"
        },
        {
          "klass": "TechLearnableMove",
          "move": "weather_ball"
        },
        {
          "klass": "TechLearnableMove",
          "move": "rock_tomb"
        },
        {
          "klass": "TechLearnableMove",
          "move": "aerial_ace"
        },
        {
          "klass": "TechLearnableMove",
          "move": "mud_shot"
        },
        {
          "klass": "TechLearnableMove",
          "move": "water_pulse"
        },
        {
          "klass": "TechLearnableMove",
          "move": "u_turn"
        },
        {
          "klass": "TechLearnableMove",
          "move": "fling"
        },
        {
          "klass": "BreedLearnableMove",
          "move": "toxic_spikes"
        },
        {
          "klass": "TechLearnableMove",
          "move": "toxic_spikes"
        },
        {
          "klass": "TechLearnableMove",
          "move": "dark_pulse"
        },
        {
          "klass": "BreedLearnableMove",
          "move": "switcheroo"
        },
        {
          "klass": "TechLearnableMove",
          "move": "giga_impact"
        },
        {
          "klass": "TechLearnableMove",
          "move": "gunk_shot"
        },
        {
          "klass": "TechLearnableMove",
          "move": "grass_knot"
        },
        {
          "klass": "TechLearnableMove",
          "move": "smack_down"
        },
        {
          "klass": "TechLearnableMove",
          "move": "sludge_wave"
        },
        {
          "klass": "TechLearnableMove",
          "move": "low_sweep"
        },
        {
          "klass": "TechLearnableMove",
          "move": "acrobatics"
        },
        {
          "klass": "BreedLearnableMove",
          "move": "retaliate"
        },
        {
          "klass": "TechLearnableMove",
          "move": "water_pledge"
        },
        {
          "klass": "EvolutionLearnableMove",
          "move": "water_shuriken"
        },
        {
          "klass": "TechLearnableMove",
          "move": "liquidation"
        },
        {
          "klass": "TechLearnableMove",
          "move": "tera_blast"
        },
        {
          "klass": "TechLearnableMove",
          "move": "snowscape"
        },
        {
          "klass": "TechLearnableMove",
          "move": "trailblaze"
        },
        {
          "klass": "TechLearnableMove",
          "move": "chilling_water"
        },
        {
          "klass": "TechLearnableMove",
          "move": "upper_hand"
        },
        {
          "klass": "TechLearnableMove",
          "move": "rock_smash"
        },
        {
          "klass": "TechLearnableMove",
          "move": "cut"
        },
        {
          "klass": "TechLearnableMove",
          "move": "strength"
        },
        {
          "klass": "TechLearnableMove",
          "move": "dive"
        }
      ]
    }
  ]
}